{"cameraMode":{"drawMode":0,"name":"Shaded","section":"Shading Mode"},"sceneLighting":false,"audioPlay":false,"sceneViewState":{"showFog":true,"showMaterialUpdate":false,"showSkybox":false,"showFlares":true,"showImageEffects":true,"showParticleSystems":true},"in2DMode":false,"pivot":{"x":-0.12142711877822876,"y":-11.049531936645508,"z":10.31640625},"rotation":{"x":0.23249560594558717,"y":-0.2543758153915405,"z":0.06315108388662338,"w":0.9366335868835449},"size":8.641156196594239,"orthographic":false}